thread_test/__init__.py
thread_test/thread-test.py
thread_test-0.1.0.dist-info/METADATA
thread_test-0.1.0.dist-info/WHEEL
thread_test-0.1.0.dist-info/RECORD
