Metadata-Version: 2.1
Name: thread-test
Version: 0.1.0
Summary: 
Author: Nicolas Aguirre
Author-email: nicolas.aguirrecampi@cencosud.com.uy
Requires-Python: >=3.11,<4.0
Classifier: Programming Language :: Python :: 3
Classifier: Programming Language :: Python :: 3.11
Requires-Dist: schedule (>=1.2.0,<2.0.0)
